x_evolution/__init__.py
x_evolution/x_evolution.py
x_evolution-0.1.26.dist-info/METADATA
x_evolution-0.1.26.dist-info/WHEEL
x_evolution-0.1.26.dist-info/licenses/LICENSE
x_evolution-0.1.26.dist-info/RECORD
