Metadata-Version: 2.4
Name: x-evolution
Version: 0.1.26
Summary: x-evolution
Project-URL: Homepage, https://pypi.org/project/x-evolution/
Project-URL: Repository, https://github.com/lucidrains/x-evolution
Author-email: Phil Wang <lucidrains@gmail.com>
License: MIT License
License-File: LICENSE
Keywords: artificial intelligence,evolution,evolutionary algorithms
Classifier: Development Status :: 4 - Beta
Classifier: Intended Audience :: Developers
Classifier: License :: OSI Approved :: MIT License
Classifier: Programming Language :: Python :: 3.9
Classifier: Topic :: Scientific/Engineering :: Artificial Intelligence
Requires-Python: >=3.9
Requires-Dist: accelerate
Requires-Dist: beartype
Requires-Dist: einops>=0.8.0
Requires-Dist: torch>=2.4
Requires-Dist: x-mlps-pytorch>=0.2.0
Requires-Dist: x-transformers>=2.11.23
Provides-Extra: examples
Requires-Dist: gymnasium[box2d]>=1.0.0; extra == 'examples'
Requires-Dist: gymnasium[mujoco]>=1.0.0; extra == 'examples'
Requires-Dist: gymnasium[other]; extra == 'examples'
Provides-Extra: test
Requires-Dist: pytest; extra == 'test'
